clibactdb.cpython-38-darwin.so
libactdb-0.0.1.dist-info/RECORD
libactdb-0.0.1.dist-info/WHEEL
libactdb-0.0.1.dist-info/top_level.txt
libactdb-0.0.1.dist-info/METADATA
libactdb/__init__.py
