Metadata-Version: 2.1
Name: libactdb
Version: 0.0.1
Summary: Activations DB
Requires-Dist: Cython
Requires-Dist: torch
Requires-Dist: numpy
Requires-Dist: h5py
